bda_flask_middleware/__init__.py
bda_flask_middleware/flasktest.py
bda_flask_middleware-0.1.0.dist-info/METADATA
bda_flask_middleware-0.1.0.dist-info/WHEEL
bda_flask_middleware-0.1.0.dist-info/top_level.txt
bda_flask_middleware-0.1.0.dist-info/RECORD
